webtool/__init__.py
webtool/application.py
webtool/deploy.sh
webtool/running.log
webtool/schema.sql
webtool/static/css/custom.css
webtool/static/css/pure-min.css
webtool/static/css/style.css
webtool/static/favicon.ico
webtool/static/guide/XMind测试用例模板.xmind
webtool/static/guide/demo1_convert_result.png
webtool/static/guide/demo2_convert_result.png
webtool/static/guide/index.html
webtool/static/guide/index.md
webtool/static/guide/pypi_upload.png
webtool/static/guide/testcase_json_demo.png
webtool/static/guide/testcase_template_demo1.png
webtool/static/guide/testcase_template_demo2.png
webtool/static/guide/testcase_template_demo3.png
webtool/static/guide/testlink.png
webtool/static/guide/testlink_import_result.png
webtool/static/guide/testlink_select_file.png
webtool/static/guide/testlink_testcase_view.png
webtool/static/guide/testsuite_json_demo.png
webtool/static/guide/webtool.png
webtool/static/guide/webtool_cli.png
webtool/static/guide/xmind_testcase_demo.png
webtool/static/guide/xmind_testcase_template_rule.png
webtool/static/guide/xmind_testcase_template_rule1.png
webtool/static/guide/xmind_to_testcase_preview.png
webtool/static/guide/zentao_import_file.png
webtool/static/guide/zentao_import_result.png
webtool/static/guide/zentao_testcase_template.png
webtool/templates/index.html
webtool/templates/preview.html
xmind2case/__about__.py
xmind2case/__init__.py
xmind2case/api.py
xmind2case/cli.py
xmind2case/const.py
xmind2case/metadata.py
xmind2case/parser.py
xmind2case/testlink.py
xmind2case/utils.py
xmind2case/zentao.py
xmind2case-1.0.9.dist-info/entry_points.txt
xmind2case-1.0.9.dist-info/LICENSE
xmind2case-1.0.9.dist-info/WHEEL
xmind2case-1.0.9.dist-info/METADATA
xmind2case-1.0.9.dist-info/RECORD
