Metadata-Version: 2.1
Name: xmind2case
Version: 1.0.9
Summary: xmind to csv
License: MIT
Author: xuanke
Author-email: zhouliwei1989@126.com
Requires-Python: >=3.7,<4.0
Classifier: License :: OSI Approved :: MIT License
Classifier: Programming Language :: Python :: 3
Classifier: Programming Language :: Python :: 3.7
Classifier: Programming Language :: Python :: 3.8
Requires-Dist: arrow (>=0.15.8,<0.16.0)
Requires-Dist: flask (>=1.1.2,<2.0.0)
Requires-Dist: requests (>=2.24.0,<3.0.0)
Requires-Dist: xmind (>=1.2.0,<2.0.0)
